<?xml version="1.0" encoding="utf-8"?><DEFECTS><DEFECT><SFA><FILEPATH>d:\project4\clientgui-wpf\filesystem\</FILEPATH><FILENAME>filesystem.cpp</FILENAME><LINE>307</LINE><COLUMN>16</COLUMN></SFA><DEFECTCODE>6282</DEFECTCODE><DESCRIPTION>Incorrect operator:  assignment of constant in Boolean context. Consider using '==' instead.</DESCRIPTION><FUNCTION>FileSystem::File::isGood</FUNCTION><DECORATED>?isGood@File@FileSystem@@QAE_NXZ</DECORATED><FUNCLINE>299</FUNCLINE><PATH /></DEFECT><DEFECT><SFA><FILEPATH>d:\project4\clientgui-wpf\filesystem\</FILEPATH><FILENAME>filesystem.cpp</FILENAME><LINE>401</LINE><COLUMN>10</COLUMN></SFA><DEFECTCODE>6102</DEFECTCODE><DESCRIPTION>Using 'st' from failed function call at line '400'.</DESCRIPTION><FUNCTION>FileSystem::FileInfo::date</FUNCTION><DECORATED>?date@FileInfo@FileSystem@@QBE?AV?$basic_string@DU?$char_traits@D@std@@V?$allocator@D@2@@std@@W4dateFormat@12@@Z</DECORATED><FUNCLINE>394</FUNCLINE><PROBABILITY>1</PROBABILITY><RANK>3</RANK><CATEGORY><RULECATEGORY>mspft</RULECATEGORY></CATEGORY><PATH><SFA><FILEPATH>d:\project4\clientgui-wpf\filesystem\</FILEPATH><FILENAME>filesystem.cpp</FILENAME><LINE>396</LINE><COLUMN>14</COLUMN></SFA><SFA><FILEPATH>d:\project4\clientgui-wpf\filesystem\</FILEPATH><FILENAME>filesystem.cpp</FILENAME><LINE>396</LINE><COLUMN>23</COLUMN></SFA><SFA><FILEPATH>d:\project4\clientgui-wpf\filesystem\</FILEPATH><FILENAME>filesystem.cpp</FILENAME><LINE>397</LINE><COLUMN>11</COLUMN></SFA><SFA><FILEPATH>d:\project4\clientgui-wpf\filesystem\</FILEPATH><FILENAME>filesystem.cpp</FILENAME><LINE>398</LINE><COLUMN>13</COLUMN></SFA><SFA><FILEPATH>d:\project4\clientgui-wpf\filesystem\</FILEPATH><FILENAME>filesystem.cpp</FILENAME><LINE>399</LINE><COLUMN>27</COLUMN></SFA><SFA><FILEPATH>d:\project4\clientgui-wpf\filesystem\</FILEPATH><FILENAME>filesystem.cpp</FILENAME><LINE>400</LINE><COLUMN>24</COLUMN><KEYEVENT><ID>1</ID><KIND>declaration</KIND><IMPORTANCE>Essential</IMPORTANCE><MESSAGE>'st' is not initialized</MESSAGE></KEYEVENT></SFA><SFA><FILEPATH>d:\project4\clientgui-wpf\filesystem\</FILEPATH><FILENAME>filesystem.cpp</FILENAME><LINE>401</LINE><COLUMN>10</COLUMN><KEYEVENT><ID>2</ID><KIND>declaration</KIND><IMPORTANCE>Full</IMPORTANCE><MESSAGE>'st' is an In/Out argument to 'FileSystem::FileInfo::intToString' (declared at d:\project4\clientgui-wpf\filesystem\filesystem.h:213)</MESSAGE></KEYEVENT></SFA><SFA><FILEPATH>d:\project4\clientgui-wpf\filesystem\</FILEPATH><FILENAME>filesystem.cpp</FILENAME><LINE>401</LINE><COLUMN>10</COLUMN><KEYEVENT><ID>3</ID><KIND>usage</KIND><IMPORTANCE>Essential</IMPORTANCE><MESSAGE>'st' is used, but may not have been initialized</MESSAGE></KEYEVENT></SFA></PATH></DEFECT><DEFECT><SFA><FILEPATH>d:\project4\clientgui-wpf\filesystem\</FILEPATH><FILENAME>filesystem.cpp</FILENAME><LINE>556</LINE><COLUMN>15</COLUMN></SFA><DEFECTCODE>6246</DEFECTCODE><DESCRIPTION>Local declaration of 'pos' hides declaration of the same name in outer scope. For additional information, see previous declaration at line '544' of 'd:\project4\clientgui-wpf\filesystem\filesystem.cpp'.</DESCRIPTION><FUNCTION>FileSystem::Path::getName</FUNCTION><DECORATED>?getName@Path@FileSystem@@SA?AV?$basic_string@DU?$char_traits@D@std@@V?$allocator@D@2@@std@@ABV34@_N@Z</DECORATED><FUNCLINE>542</FUNCLINE><PATH><SFA><FILEPATH>d:\project4\clientgui-wpf\filesystem\</FILEPATH><FILENAME>filesystem.cpp</FILENAME><LINE>544</LINE><COLUMN>9</COLUMN></SFA></PATH></DEFECT><DEFECT><SFA><FILEPATH>d:\project4\clientgui-wpf\sockets\</FILEPATH><FILENAME>sockets.cpp</FILENAME><LINE>237</LINE><COLUMN>15</COLUMN></SFA><DEFECTCODE>6001</DEFECTCODE><DESCRIPTION>Using uninitialized memory 'ret'.</DESCRIPTION><FUNCTION>Socket::bytesWaiting</FUNCTION><DECORATED>?bytesWaiting@Socket@@QAEIXZ</DECORATED><FUNCLINE>234</FUNCLINE><PROBABILITY>1</PROBABILITY><RANK>3</RANK><CATEGORY><RULECATEGORY>mspft</RULECATEGORY></CATEGORY><PATH><SFA><FILEPATH>d:\project4\clientgui-wpf\sockets\</FILEPATH><FILENAME>sockets.cpp</FILENAME><LINE>236</LINE><COLUMN>20</COLUMN><KEYEVENT><ID>1</ID><KIND>declaration</KIND><IMPORTANCE>Essential</IMPORTANCE><MESSAGE>'ret' is not initialized</MESSAGE></KEYEVENT></SFA><SFA><FILEPATH>d:\project4\clientgui-wpf\sockets\</FILEPATH><FILENAME>sockets.cpp</FILENAME><LINE>237</LINE><COLUMN>15</COLUMN><KEYEVENT><ID>2</ID><KIND>declaration</KIND><IMPORTANCE>Full</IMPORTANCE><MESSAGE>'ret' is an In/Out argument to 'ioctlsocket' (declared at c:\program files (x86)\windows kits\8.1\include\um\winsock2.h:1658)</MESSAGE></KEYEVENT></SFA><SFA><FILEPATH>d:\project4\clientgui-wpf\sockets\</FILEPATH><FILENAME>sockets.cpp</FILENAME><LINE>237</LINE><COLUMN>15</COLUMN><KEYEVENT><ID>3</ID><KIND>usage</KIND><IMPORTANCE>Essential</IMPORTANCE><MESSAGE>'ret' is used, but may not have been initialized</MESSAGE></KEYEVENT></SFA></PATH></DEFECT></DEFECTS>